plsl/__init__.py
plsl/formating.py
plsl/plsl.py
plsl-0.3.data/data/lib/site-packages/plsl/static/icon.png
plsl-0.3.data/data/lib/site-packages/plsl/static/logo.png
plsl-0.3.data/data/lib/site-packages/plsl/templates/index.html
plsl-0.3.dist-info/LICENSE
plsl-0.3.dist-info/METADATA
plsl-0.3.dist-info/WHEEL
plsl-0.3.dist-info/top_level.txt
plsl-0.3.dist-info/RECORD
