Metadata-Version: 2.1
Name: plsl
Version: 0.3
Summary: Python code logging with a server interface
Home-page: https://github.com/tory1103/pls-logging
Author: Adrián Toral
Author-email: adriantoral@sertor.es
License: UNKNOWN
Project-URL: Website, https://github.com/tory1103/pls-logging
Project-URL: Issues, https://github.com/tory1103/pls-logging/issues
Keywords: python,flask,gui,server,logging,python3,server-gui,localhost
Platform: UNKNOWN
Classifier: Programming Language :: Python :: 3
Classifier: License :: OSI Approved :: GNU General Public License v3 (GPLv3)
Classifier: Operating System :: OS Independent
Classifier: Topic :: System :: Logging
Requires-Python: >=3.6
License-File: LICENSE
Requires-Dist: oh-my-pickledb (==4)
Requires-Dist: Flask (>=2.0.1)
